LICENSE.txt
README.md
setup.cfg
setup.py
thread_lfanke/__init__.py
thread_lfanke/thread_lfanke.py
thread_lfanke.egg-info/PKG-INFO
thread_lfanke.egg-info/SOURCES.txt
thread_lfanke.egg-info/dependency_links.txt
thread_lfanke.egg-info/top_level.txt